mathstrovehiclesim/__init__.py
mathstrovehiclesim/demo.py
mathstrovehiclesim/environment.py
mathstrovehiclesim/globals.py
mathstrovehiclesim/host_vehicle.py
mathstrovehiclesim/simulation_cfg.json
mathstrovehiclesim/simulator.py
mathstrovehiclesim/traffic.py
mathstrovehiclesim/traffic_router.py
mathstrovehiclesim/utils.py
mathstrovehiclesim/vehicle.py
mathstrovehiclesim/demo_images/actions/error.png
mathstrovehiclesim/demo_images/actions/disappear/disappear_01.png
mathstrovehiclesim/demo_images/actions/disappear/disappear_02.png
mathstrovehiclesim/demo_images/actions/disappear/disappear_03.png
mathstrovehiclesim/demo_images/actions/disappear/disappear_04.png
mathstrovehiclesim/demo_images/actions/disappear/disappear_05.png
mathstrovehiclesim/demo_images/actions/disappear/disappear_06.png
mathstrovehiclesim/demo_images/actions/disappear/disappear_07.png
mathstrovehiclesim/demo_images/actions/distort/distort_01.png
mathstrovehiclesim/demo_images/actions/distort/distort_02.png
mathstrovehiclesim/demo_images/actions/distort/distort_03.png
mathstrovehiclesim/demo_images/actions/distort/distort_04.png
mathstrovehiclesim/demo_images/actions/distort/distort_05.png
mathstrovehiclesim/demo_images/actions/distort/distort_06.png
mathstrovehiclesim/demo_images/actions/distort/distort_07.png
mathstrovehiclesim/demo_images/actions/shrink/shrink_01.png
mathstrovehiclesim/demo_images/actions/shrink/shrink_02.png
mathstrovehiclesim/demo_images/actions/shrink/shrink_03.png
mathstrovehiclesim/demo_images/actions/shrink/shrink_04.png
mathstrovehiclesim/demo_images/actions/shrink/shrink_05.png
mathstrovehiclesim/demo_images/actions/shrink/shrink_06.png
mathstrovehiclesim/demo_images/actions/shrink/shrink_07.png
mathstrovehiclesim/demo_images/actions/squeeze/squeeze_01.png
mathstrovehiclesim/demo_images/actions/squeeze/squeeze_02.png
mathstrovehiclesim/demo_images/actions/squeeze/squeeze_03.png
mathstrovehiclesim/demo_images/actions/squeeze/squeeze_04.png
mathstrovehiclesim-2.0.8.dist-info/METADATA
mathstrovehiclesim-2.0.8.dist-info/WHEEL
mathstrovehiclesim-2.0.8.dist-info/top_level.txt
mathstrovehiclesim-2.0.8.dist-info/RECORD
